{
  "id": "2446783",
  "name": "驰骋",
  "font_family": "iconfont",
  "css_prefix_text": "icon-",
  "description": "",
  "glyphs": [
    {
      "icon_id": "304006",
      "name": "地图",
      "font_class": "map",
      "unicode": "e6da",
      "unicode_decimal": 59098
    },
    {
      "icon_id": "1656345",
      "name": "人民币",
      "font_class": "renminbi",
      "unicode": "e668",
      "unicode_decimal": 58984
    },
    {
      "icon_id": "2471358",
      "name": "富文本框",
      "font_class": "fuwenbenkuang",
      "unicode": "e66f",
      "unicode_decimal": 58991
    },
    {
      "icon_id": "3459817",
      "name": "身份证",
      "font_class": "shenfenzheng",
      "unicode": "e666",
      "unicode_decimal": 58982
    },
    {
      "icon_id": "4387824",
      "name": "字段列表",
      "font_class": "ziduanliebiao",
      "unicode": "e67b",
      "unicode_decimal": 59003
    },
    {
      "icon_id": "4427197",
      "name": "定位",
      "font_class": "dingwei",
      "unicode": "e66b",
      "unicode_decimal": 58987
    },
    {
      "icon_id": "6251158",
      "name": "写字",
      "font_class": "xiezi",
      "unicode": "e66c",
      "unicode_decimal": 58988
    },
    {
      "icon_id": "6335528",
      "name": "图片附件",
      "font_class": "tupianfujian",
      "unicode": "e66e",
      "unicode_decimal": 58990
    },
    {
      "icon_id": "6480153",
      "name": "时间",
      "font_class": "shijian",
      "unicode": "e6a8",
      "unicode_decimal": 59048
    },
    {
      "icon_id": "7088564",
      "name": "261已发布票据-人民币-细",
      "font_class": "yifabupiaoju-renminbi-xi",
      "unicode": "e724",
      "unicode_decimal": 59172
    },
    {
      "icon_id": "7596638",
      "name": "html",
      "font_class": "html",
      "unicode": "e69b",
      "unicode_decimal": 59035
    },
    {
      "icon_id": "7603875",
      "name": "评分",
      "font_class": "pingfen",
      "unicode": "e670",
      "unicode_decimal": 58992
    },
    {
      "icon_id": "8690805",
      "name": "表格附件",
      "font_class": "biaogefujian",
      "unicode": "e6bc",
      "unicode_decimal": 59068
    },
    {
      "icon_id": "9120438",
      "name": "附件",
      "font_class": "attach",
      "unicode": "e671",
      "unicode_decimal": 58993
    },
    {
      "icon_id": "9144401",
      "name": "复选框",
      "font_class": "fuxuankuang",
      "unicode": "e73d",
      "unicode_decimal": 59197
    },
    {
      "icon_id": "9144404",
      "name": "单选按钮",
      "font_class": "danxuananniu",
      "unicode": "e73e",
      "unicode_decimal": 59198
    },
    {
      "icon_id": "9468080",
      "name": "下拉框 表单",
      "font_class": "xialakuangbiaodan",
      "unicode": "e672",
      "unicode_decimal": 58994
    },
    {
      "icon_id": "9856182",
      "name": "审核",
      "font_class": "shenhe1",
      "unicode": "e67e",
      "unicode_decimal": 59006
    },
    {
      "icon_id": "9980399",
      "name": "下拉框",
      "font_class": "xialakuang",
      "unicode": "e6c9",
      "unicode_decimal": 59081
    },
    {
      "icon_id": "10176557",
      "name": "时间",
      "font_class": "shijian1",
      "unicode": "e6ef",
      "unicode_decimal": 59119
    },
    {
      "icon_id": "10885920",
      "name": "按钮",
      "font_class": "anniu",
      "unicode": "e8c5",
      "unicode_decimal": 59589
    },
    {
      "icon_id": "10904768",
      "name": "字段类型-整数",
      "font_class": "ziduanleixing-zhengshu",
      "unicode": "e675",
      "unicode_decimal": 58997
    },
    {
      "icon_id": "10907065",
      "name": "下拉框",
      "font_class": "xialakuang1",
      "unicode": "e8ca",
      "unicode_decimal": 59594
    },
    {
      "icon_id": "11052280",
      "name": "字段",
      "font_class": "ziduan1",
      "unicode": "e6bf",
      "unicode_decimal": 59071
    },
    {
      "icon_id": "17834746",
      "name": "日期 期数",
      "font_class": "riqiqishu",
      "unicode": "e678",
      "unicode_decimal": 59000
    },
    {
      "icon_id": "19243466",
      "name": "ptkj-连续签批模式",
      "font_class": "ptkj-lianxuqianpimoshi",
      "unicode": "e984",
      "unicode_decimal": 59780
    },
    {
      "icon_id": "19313106",
      "name": "整数",
      "font_class": "zhengshu",
      "unicode": "e877",
      "unicode_decimal": 59511
    },
    {
      "icon_id": "20798269",
      "name": "超链接",
      "font_class": "chaolianjie",
      "unicode": "e6a7",
      "unicode_decimal": 59047
    },
    {
      "icon_id": "21125186",
      "name": "单选",
      "font_class": "danxuan",
      "unicode": "e679",
      "unicode_decimal": 59001
    },
    {
      "icon_id": "21853002",
      "name": "超链接",
      "font_class": "chaolianjie1",
      "unicode": "e6c0",
      "unicode_decimal": 59072
    },
    {
      "icon_id": "9943725",
      "name": "双箭头",
      "font_class": "double-extend-left",
      "unicode": "e663",
      "unicode_decimal": 58979
    },
    {
      "icon_id": "10377937",
      "name": "双箭头",
      "font_class": "shuangjiantou1",
      "unicode": "e664",
      "unicode_decimal": 58980
    },
    {
      "icon_id": "5639772",
      "name": "双箭头",
      "font_class": "shuangjiantou",
      "unicode": "e661",
      "unicode_decimal": 58977
    },
    {
      "icon_id": "5639859",
      "name": "双箭头",
      "font_class": "you2",
      "unicode": "e662",
      "unicode_decimal": 58978
    },
    {
      "icon_id": "9478212",
      "name": "流程",
      "font_class": "liucheng1",
      "unicode": "e65e",
      "unicode_decimal": 58974
    },
    {
      "icon_id": "13184902",
      "name": "表单",
      "font_class": "biaodan",
      "unicode": "e660",
      "unicode_decimal": 58976
    },
    {
      "icon_id": "19640549",
      "name": "设 置",
      "font_class": "shezhi",
      "unicode": "e677",
      "unicode_decimal": 58999
    },
    {
      "icon_id": "10973189",
      "name": "book",
      "font_class": "book",
      "unicode": "e7bc",
      "unicode_decimal": 59324
    },
    {
      "icon_id": "11609211",
      "name": "删  除",
      "font_class": "shanchu",
      "unicode": "e6b8",
      "unicode_decimal": 59064
    },
    {
      "icon_id": "12252603",
      "name": "编辑",
      "font_class": "bianji1",
      "unicode": "e65d",
      "unicode_decimal": 58973
    },
    {
      "icon_id": "12586221",
      "name": "book",
      "font_class": "book-copy",
      "unicode": "e802",
      "unicode_decimal": 59394
    },
    {
      "icon_id": "2950798",
      "name": "新建类别",
      "font_class": "xinjianleibie",
      "unicode": "e6b5",
      "unicode_decimal": 59061
    },
    {
      "icon_id": "9935091",
      "name": "新东方-刷新图标",
      "font_class": "refresh",
      "unicode": "e656",
      "unicode_decimal": 58966
    },
    {
      "icon_id": "13352433",
      "name": "编 辑",
      "font_class": "bianji",
      "unicode": "e657",
      "unicode_decimal": 58967
    },
    {
      "icon_id": "13955399",
      "name": "新建流程",
      "font_class": "xinjianliucheng",
      "unicode": "e659",
      "unicode_decimal": 58969
    },
    {
      "icon_id": "16236456",
      "name": "导入模板",
      "font_class": "daorumoban",
      "unicode": "e65a",
      "unicode_decimal": 58970
    },
    {
      "icon_id": "17560018",
      "name": "上 移",
      "font_class": "xy",
      "unicode": "e65b",
      "unicode_decimal": 58971
    },
    {
      "icon_id": "17932252",
      "name": "新建",
      "font_class": "xinjian1",
      "unicode": "e856",
      "unicode_decimal": 59478
    },
    {
      "icon_id": "20062041",
      "name": "上 移",
      "font_class": "shangyi",
      "unicode": "e65c",
      "unicode_decimal": 58972
    },
    {
      "icon_id": "1053421",
      "name": "加粗 选中",
      "font_class": "jiacuxuanzhong",
      "unicode": "e71c",
      "unicode_decimal": 59164
    },
    {
      "icon_id": "1806327",
      "name": "宽度增加",
      "font_class": "kuanduzengjia",
      "unicode": "e627",
      "unicode_decimal": 58919
    },
    {
      "icon_id": "2355703",
      "name": "边框",
      "font_class": "border-top-solid",
      "unicode": "e62c",
      "unicode_decimal": 58924
    },
    {
      "icon_id": "2355746",
      "name": "边框",
      "font_class": "border-right-solid",
      "unicode": "e631",
      "unicode_decimal": 58929
    },
    {
      "icon_id": "2355751",
      "name": "边框",
      "font_class": "border-bottom-solid",
      "unicode": "e633",
      "unicode_decimal": 58931
    },
    {
      "icon_id": "3085302",
      "name": "边框",
      "font_class": "shadow-left",
      "unicode": "e64d",
      "unicode_decimal": 58957
    },
    {
      "icon_id": "4568330",
      "name": "背景颜色 ",
      "font_class": "beijingyansezhuanhuan",
      "unicode": "e64e",
      "unicode_decimal": 58958
    },
    {
      "icon_id": "4859569",
      "name": "宽度",
      "font_class": "kuandu",
      "unicode": "e652",
      "unicode_decimal": 58962
    },
    {
      "icon_id": "9466948",
      "name": "高度",
      "font_class": "gaodu",
      "unicode": "e6c3",
      "unicode_decimal": 59075
    },
    {
      "icon_id": "17413217",
      "name": "斜体",
      "font_class": "xieti",
      "unicode": "e653",
      "unicode_decimal": 58963
    },
    {
      "icon_id": "18810757",
      "name": "字体颜色",
      "font_class": "zitiyanse",
      "unicode": "e655",
      "unicode_decimal": 58965
    },
    {
      "icon_id": "20460393",
      "name": "边框",
      "font_class": "biankuang",
      "unicode": "e729",
      "unicode_decimal": 59177
    },
    {
      "icon_id": "10572254",
      "name": "框架",
      "font_class": "kuangjia",
      "unicode": "e626",
      "unicode_decimal": 58918
    },
    {
      "icon_id": "11239863",
      "name": "框架",
      "font_class": "kuangjia1",
      "unicode": "e69c",
      "unicode_decimal": 59036
    },
    {
      "icon_id": "5965316",
      "name": "审核",
      "font_class": "shenhe",
      "unicode": "e623",
      "unicode_decimal": 58915
    },
    {
      "icon_id": "7615259",
      "name": "分组",
      "font_class": "fenzu",
      "unicode": "e66d",
      "unicode_decimal": 58989
    },
    {
      "icon_id": "10371692",
      "name": "附 件 (1)",
      "font_class": "fujian",
      "unicode": "e624",
      "unicode_decimal": 58916
    },
    {
      "icon_id": "10560231",
      "name": "字段",
      "font_class": "ziduan",
      "unicode": "e625",
      "unicode_decimal": 58917
    },
    {
      "icon_id": "14442004",
      "name": "组件",
      "font_class": "zujian",
      "unicode": "e6ed",
      "unicode_decimal": 59117
    },
    {
      "icon_id": "14453321",
      "name": "数据表",
      "font_class": "tianjiashujubiao",
      "unicode": "e630",
      "unicode_decimal": 58928
    },
    {
      "icon_id": "1137788",
      "name": "系统",
      "font_class": "xitong",
      "unicode": "e67c",
      "unicode_decimal": 59004
    },
    {
      "icon_id": "2614861",
      "name": "节点",
      "font_class": "jiedian-",
      "unicode": "e65f",
      "unicode_decimal": 58975
    },
    {
      "icon_id": "2719820",
      "name": "加减乘除-02",
      "font_class": "jiajianchengchu-",
      "unicode": "e61c",
      "unicode_decimal": 58908
    },
    {
      "icon_id": "2719821",
      "name": "加减乘除-01",
      "font_class": "jiajianchengchu-1",
      "unicode": "e61d",
      "unicode_decimal": 58909
    },
    {
      "icon_id": "2971634",
      "name": "导入导出",
      "font_class": "daorudaochu",
      "unicode": "e64c",
      "unicode_decimal": 58956
    },
    {
      "icon_id": "4381548",
      "name": "新建表单",
      "font_class": "xinjianbiaodan",
      "unicode": "e618",
      "unicode_decimal": 58904
    },
    {
      "icon_id": "10538251",
      "name": "风格",
      "font_class": "fengge",
      "unicode": "ea0b",
      "unicode_decimal": 59915
    },
    {
      "icon_id": "11623076",
      "name": "风格",
      "font_class": "fengge1",
      "unicode": "e61a",
      "unicode_decimal": 58906
    },
    {
      "icon_id": "15921186",
      "name": "样式",
      "font_class": "yangshi",
      "unicode": "e674",
      "unicode_decimal": 58996
    },
    {
      "icon_id": "17445554",
      "name": "风格",
      "font_class": "fengge2",
      "unicode": "e61f",
      "unicode_decimal": 58911
    },
    {
      "icon_id": "17591120",
      "name": "手机",
      "font_class": "shouji",
      "unicode": "e6c4",
      "unicode_decimal": 59076
    },
    {
      "icon_id": "18913896",
      "name": "属性",
      "font_class": "shuxing",
      "unicode": "e622",
      "unicode_decimal": 58914
    },
    {
      "icon_id": "20174891",
      "name": "手机",
      "font_class": "shouji1",
      "unicode": "e634",
      "unicode_decimal": 58932
    },
    {
      "icon_id": "3440170",
      "name": "常用图标-飞机",
      "font_class": "feiji",
      "unicode": "e613",
      "unicode_decimal": 58899
    },
    {
      "icon_id": "354417",
      "name": "帮助",
      "font_class": "iconfonticon4",
      "unicode": "e617",
      "unicode_decimal": 58903
    },
    {
      "icon_id": "761490",
      "name": "系统高级自定义",
      "font_class": "icon",
      "unicode": "e665",
      "unicode_decimal": 58981
    },
    {
      "icon_id": "4251718",
      "name": "返回",
      "font_class": "fanhui",
      "unicode": "e641",
      "unicode_decimal": 58945
    },
    {
      "icon_id": "7103464",
      "name": "流程高级功能",
      "font_class": "liuchenggaojigongneng",
      "unicode": "e620",
      "unicode_decimal": 58912
    },
    {
      "icon_id": "9568043",
      "name": "保存",
      "font_class": "baocun1",
      "unicode": "e647",
      "unicode_decimal": 58951
    },
    {
      "icon_id": "13614062",
      "name": "导出",
      "font_class": "daochu",
      "unicode": "e650",
      "unicode_decimal": 58960
    },
    {
      "icon_id": "13614081",
      "name": "导入",
      "font_class": "daoru",
      "unicode": "e651",
      "unicode_decimal": 58961
    },
    {
      "icon_id": "14666039",
      "name": "多文件",
      "font_class": "duowenjian",
      "unicode": "e725",
      "unicode_decimal": 59173
    },
    {
      "icon_id": "14666074",
      "name": "文件",
      "font_class": "wenjian2",
      "unicode": "e72c",
      "unicode_decimal": 59180
    },
    {
      "icon_id": "15085885",
      "name": "海报分享",
      "font_class": "haibaofenxiang",
      "unicode": "e64b",
      "unicode_decimal": 58955
    },
    {
      "icon_id": "17833695",
      "name": "文件",
      "font_class": "wenjian3",
      "unicode": "e62b",
      "unicode_decimal": 58923
    },
    {
      "icon_id": "20032443",
      "name": "高级报表设置",
      "font_class": "gaojibaobiaoshezhi",
      "unicode": "e636",
      "unicode_decimal": 58934
    },
    {
      "icon_id": "18547409",
      "name": "文件夹",
      "font_class": "wenjianjia2",
      "unicode": "e60b",
      "unicode_decimal": 58891
    },
    {
      "icon_id": "9224029",
      "name": "文件",
      "font_class": "wenjian",
      "unicode": "e619",
      "unicode_decimal": 58905
    },
    {
      "icon_id": "16347614",
      "name": "文件",
      "font_class": "wenjian1",
      "unicode": "e632",
      "unicode_decimal": 58930
    },
    {
      "icon_id": "19076748",
      "name": "文件夹  开folder-open",
      "font_class": "wenjianjiakaifolder-open",
      "unicode": "e611",
      "unicode_decimal": 58897
    },
    {
      "icon_id": "19407485",
      "name": "减",
      "font_class": "jian",
      "unicode": "e851",
      "unicode_decimal": 59473
    },
    {
      "icon_id": "19944272",
      "name": "加",
      "font_class": "jia",
      "unicode": "e608",
      "unicode_decimal": 58888
    },
    {
      "icon_id": "20285504",
      "name": "文件夹",
      "font_class": "wenjianjia1",
      "unicode": "e62a",
      "unicode_decimal": 58922
    },
    {
      "icon_id": "5665003",
      "name": "管理员",
      "font_class": "guanli",
      "unicode": "e605",
      "unicode_decimal": 58885
    },
    {
      "icon_id": "12713746",
      "name": "关于",
      "font_class": "guanyu",
      "unicode": "e612",
      "unicode_decimal": 58898
    },
    {
      "icon_id": "14783508",
      "name": "退出",
      "font_class": "tuichu",
      "unicode": "e61e",
      "unicode_decimal": 58910
    },
    {
      "icon_id": "20153247",
      "name": "首页-选中",
      "font_class": "home-copy",
      "unicode": "e606",
      "unicode_decimal": 58886
    },
    {
      "icon_id": "20268080",
      "name": "个人",
      "font_class": "geren",
      "unicode": "e607",
      "unicode_decimal": 58887
    },
    {
      "icon_id": "7411038",
      "name": "线程",
      "font_class": "xiancheng",
      "unicode": "e64a",
      "unicode_decimal": 58954
    },
    {
      "icon_id": "7692482",
      "name": "线程",
      "font_class": "xiancheng1",
      "unicode": "e673",
      "unicode_decimal": 58995
    },
    {
      "icon_id": "7910158",
      "name": "线程查看",
      "font_class": "xianchengchakan",
      "unicode": "e645",
      "unicode_decimal": 58949
    },
    {
      "icon_id": "7941758",
      "name": "线程栈",
      "font_class": "xianchengzhan",
      "unicode": "e64f",
      "unicode_decimal": 58959
    },
    {
      "icon_id": "8534544",
      "name": "线程泄漏",
      "font_class": "xianchengxielou",
      "unicode": "e676",
      "unicode_decimal": 58998
    },
    {
      "icon_id": "11658876",
      "name": "首页-线程-01",
      "font_class": "shouye-xiancheng-",
      "unicode": "e635",
      "unicode_decimal": 58933
    },
    {
      "icon_id": "17216670",
      "name": "多线程组件",
      "font_class": "duoxianchengzujian",
      "unicode": "e62f",
      "unicode_decimal": 58927
    },
    {
      "icon_id": "19793134",
      "name": "线程追踪",
      "font_class": "xianchengzhuizong",
      "unicode": "e721",
      "unicode_decimal": 59169
    },
    {
      "icon_id": "19908592",
      "name": "线程",
      "font_class": "xiancheng2",
      "unicode": "e732",
      "unicode_decimal": 59186
    },
    {
      "icon_id": "1032410",
      "name": "星星",
      "font_class": "xingxing",
      "unicode": "e643",
      "unicode_decimal": 58947
    },
    {
      "icon_id": "1104516",
      "name": "节点类_中心管理",
      "font_class": "jiedianleizhongxinguanli",
      "unicode": "e9cf",
      "unicode_decimal": 59855
    },
    {
      "icon_id": "1104517",
      "name": "节点类_主控中心1",
      "font_class": "jiedianleizhukongzhongxin1",
      "unicode": "e9d0",
      "unicode_decimal": 59856
    },
    {
      "icon_id": "2028246",
      "name": "发起人",
      "font_class": "sponsor",
      "unicode": "e6e5",
      "unicode_decimal": 59109
    },
    {
      "icon_id": "10352320",
      "name": "表格 - 显示",
      "font_class": "biaoge-xianshi",
      "unicode": "e616",
      "unicode_decimal": 58902
    },
    {
      "icon_id": "15558737",
      "name": "节点",
      "font_class": "jiedian",
      "unicode": "e699",
      "unicode_decimal": 59033
    },
    {
      "icon_id": "16800966",
      "name": "节点",
      "font_class": "jiedian1",
      "unicode": "e61b",
      "unicode_decimal": 58907
    },
    {
      "icon_id": "17822200",
      "name": "临时表格",
      "font_class": "linshibiaoge",
      "unicode": "e6c2",
      "unicode_decimal": 59074
    },
    {
      "icon_id": "19134704",
      "name": "01 主数据_条件类型",
      "font_class": "01zhushuju_tiaojianleixing",
      "unicode": "e60e",
      "unicode_decimal": 58894
    },
    {
      "icon_id": "20104497",
      "name": "节点管理_1",
      "font_class": "jiedianguanli_1",
      "unicode": "e615",
      "unicode_decimal": 58901
    },
    {
      "icon_id": "551962",
      "name": "箭头",
      "font_class": "arrow-right",
      "unicode": "e604",
      "unicode_decimal": 58884
    },
    {
      "icon_id": "810220",
      "name": "箭头",
      "font_class": "jiantou-copy",
      "unicode": "e667",
      "unicode_decimal": 58983
    },
    {
      "icon_id": "584254",
      "name": "箭头",
      "font_class": "iconfontjiantou",
      "unicode": "e640",
      "unicode_decimal": 58944
    },
    {
      "icon_id": "810222",
      "name": "箭头",
      "font_class": "jiantou-copy-copy-copy",
      "unicode": "e66a",
      "unicode_decimal": 58986
    },
    {
      "icon_id": "5961297",
      "name": "查询",
      "font_class": "Search",
      "unicode": "ec4c",
      "unicode_decimal": 60492
    },
    {
      "icon_id": "9697576",
      "name": "关注",
      "font_class": "Focus",
      "unicode": "e62e",
      "unicode_decimal": 58926
    },
    {
      "icon_id": "10143418",
      "name": "确定",
      "font_class": "queding",
      "unicode": "e610",
      "unicode_decimal": 58896
    },
    {
      "icon_id": "12686744",
      "name": "移交",
      "font_class": "Shift",
      "unicode": "e649",
      "unicode_decimal": 58953
    },
    {
      "icon_id": "12719934",
      "name": "保存",
      "font_class": "Save",
      "unicode": "e60d",
      "unicode_decimal": 58893
    },
    {
      "icon_id": "14434800",
      "name": "发送",
      "font_class": "Send",
      "unicode": "e63f",
      "unicode_decimal": 58943
    },
    {
      "icon_id": "16206710",
      "name": "历史轨迹",
      "font_class": "Track",
      "unicode": "e6ac",
      "unicode_decimal": 59052
    },
    {
      "icon_id": "16921545",
      "name": "关闭",
      "font_class": "guanbi",
      "unicode": "e7e8",
      "unicode_decimal": 59368
    },
    {
      "icon_id": "609629",
      "name": "文件夹",
      "font_class": "wenjianjiafolder80",
      "unicode": "e743",
      "unicode_decimal": 59203
    },
    {
      "icon_id": "8765245",
      "name": "文件夹-2",
      "font_class": "wenjianjia-",
      "unicode": "e63a",
      "unicode_decimal": 58938
    },
    {
      "icon_id": "8765246",
      "name": "文件夹-1",
      "font_class": "wenjianjia-1",
      "unicode": "e63d",
      "unicode_decimal": 58941
    },
    {
      "icon_id": "1029145",
      "name": "文件夹",
      "font_class": "wenjianjiak",
      "unicode": "e644",
      "unicode_decimal": 58948
    },
    {
      "icon_id": "15779744",
      "name": "文件夹",
      "font_class": "wenjianjia",
      "unicode": "e642",
      "unicode_decimal": 58946
    },
    {
      "icon_id": "9148956",
      "name": "箭头",
      "font_class": "weimingmingwenjianjia_jiantou",
      "unicode": "e638",
      "unicode_decimal": 58936
    },
    {
      "icon_id": "1503655",
      "name": "表格",
      "font_class": "biaoge",
      "unicode": "e637",
      "unicode_decimal": 58935
    },
    {
      "icon_id": "1509745",
      "name": "添加",
      "font_class": "add",
      "unicode": "e669",
      "unicode_decimal": 58985
    },
    {
      "icon_id": "4409281",
      "name": "读书",
      "font_class": "ziyuan",
      "unicode": "e628",
      "unicode_decimal": 58920
    },
    {
      "icon_id": "9149482",
      "name": "可编辑表格",
      "font_class": "kebianjibiaoge",
      "unicode": "e720",
      "unicode_decimal": 59168
    },
    {
      "icon_id": "10789851",
      "name": "批量设置_操作_jurassic",
      "font_class": "jurassic_setup-batch",
      "unicode": "e6cf",
      "unicode_decimal": 59087
    },
    {
      "icon_id": "11493956",
      "name": "禁用",
      "font_class": "jinyong",
      "unicode": "e629",
      "unicode_decimal": 58921
    },
    {
      "icon_id": "17710202",
      "name": "启用",
      "font_class": "qiyong",
      "unicode": "e7f3",
      "unicode_decimal": 59379
    },
    {
      "icon_id": "18311262",
      "name": "删 除",
      "font_class": "shanchu1",
      "unicode": "e63c",
      "unicode_decimal": 58940
    },
    {
      "icon_id": "4997342",
      "name": "属性-收起",
      "font_class": "shuxing-shouqi",
      "unicode": "e639",
      "unicode_decimal": 58937
    },
    {
      "icon_id": "5057244",
      "name": "标签",
      "font_class": "biaoqian2",
      "unicode": "e60c",
      "unicode_decimal": 58892
    },
    {
      "icon_id": "16136910",
      "name": "标签",
      "font_class": "biaoqian3",
      "unicode": "e603",
      "unicode_decimal": 58883
    },
    {
      "icon_id": "20406397",
      "name": "标签",
      "font_class": "biaoqian4",
      "unicode": "e784",
      "unicode_decimal": 59268
    },
    {
      "icon_id": "3447466",
      "name": "服务编排-连接线",
      "font_class": "lianjiexian",
      "unicode": "e75b",
      "unicode_decimal": 59227
    },
    {
      "icon_id": "5072121",
      "name": "标签+",
      "font_class": "biaoqian",
      "unicode": "e63b",
      "unicode_decimal": 58939
    },
    {
      "icon_id": "15517652",
      "name": "搜索",
      "font_class": "sousuo",
      "unicode": "e602",
      "unicode_decimal": 58882
    },
    {
      "icon_id": "16200188",
      "name": "标签",
      "font_class": "biaoqian1",
      "unicode": "e9a1",
      "unicode_decimal": 59809
    },
    {
      "icon_id": "18769656",
      "name": "节点",
      "font_class": "node",
      "unicode": "e614",
      "unicode_decimal": 58900
    },
    {
      "icon_id": "4641173",
      "name": "保存",
      "font_class": "baocun",
      "unicode": "e62d",
      "unicode_decimal": 58925
    },
    {
      "icon_id": "6056181",
      "name": "帮助",
      "font_class": "help",
      "unicode": "e60a",
      "unicode_decimal": 58890
    },
    {
      "icon_id": "6183154",
      "name": "流程",
      "font_class": "flow-line",
      "unicode": "e63e",
      "unicode_decimal": 58942
    },
    {
      "icon_id": "9748106",
      "name": "测试",
      "font_class": "ceshi",
      "unicode": "e648",
      "unicode_decimal": 58952
    },
    {
      "icon_id": "12719942",
      "name": "新建",
      "font_class": "xinjian",
      "unicode": "e60f",
      "unicode_decimal": 58895
    },
    {
      "icon_id": "17204066",
      "name": "流程",
      "font_class": "xianxingtubiaozhizuomoban-43",
      "unicode": "e621",
      "unicode_decimal": 58913
    },
    {
      "icon_id": "17817458",
      "name": "首页",
      "font_class": "shouye",
      "unicode": "e601",
      "unicode_decimal": 58881
    },
    {
      "icon_id": "5922268",
      "name": "74_流程实例",
      "font_class": "_liuchengshili",
      "unicode": "e609",
      "unicode_decimal": 58889
    },
    {
      "icon_id": "6773155",
      "name": "文件-退回文件",
      "font_class": "wj-thwj",
      "unicode": "e757",
      "unicode_decimal": 59223
    },
    {
      "icon_id": "7898688",
      "name": "管理员",
      "font_class": "guanliyuan",
      "unicode": "e600",
      "unicode_decimal": 58880
    },
    {
      "icon_id": "9540066",
      "name": "案例",
      "font_class": "anli",
      "unicode": "e658",
      "unicode_decimal": 58968
    },
    {
      "icon_id": "15797082",
      "name": "【视图】节点显示",
      "font_class": "shitujiedianxianshi",
      "unicode": "e654",
      "unicode_decimal": 58964
    },
    {
      "icon_id": "16103129",
      "name": "表单定制（模版）",
      "font_class": "biaodandingzhimoban",
      "unicode": "e646",
      "unicode_decimal": 58950
    },
    {
      "icon_id": "16517969",
      "name": "待办",
      "font_class": "daiban",
      "unicode": "e6be",
      "unicode_decimal": 59070
    },
    {
      "icon_id": "18735870",
      "name": "流程",
      "font_class": "liucheng",
      "unicode": "e6d6",
      "unicode_decimal": 59094
    }
  ]
}
